vectormesh/__init__.py
vectormesh/types.py
vectormesh/components/__init__.py
vectormesh/components/aggregation.py
vectormesh/components/connectors.py
vectormesh/components/gating.py
vectormesh/components/metrics.py
vectormesh/components/neural.py
vectormesh/components/padding.py
vectormesh/components/pipelines.py
vectormesh/data/__init__.py
vectormesh/data/cache.py
vectormesh/data/dataset.py
vectormesh/data/summarize.py
vectormesh/data/vectorizers.py
vectormesh-0.1.0.dist-info/METADATA
vectormesh-0.1.0.dist-info/WHEEL
vectormesh-0.1.0.dist-info/entry_points.txt
vectormesh-0.1.0.dist-info/RECORD
