Metadata-Version: 2.4
Name: vectormesh
Version: 0.1.0
Summary: Add your description here
Author-email: raoul grouls <Raoul.Grouls@han.nl>
Requires-Python: >=3.12
Requires-Dist: beartype>=0.22.9
Requires-Dist: datasets>=4.4.2
Requires-Dist: fastmcp>=2.14.2
Requires-Dist: jaxtyping>=0.3.4
Requires-Dist: loguru>=0.7.3
Requires-Dist: mltrainer>=0.2.7
Requires-Dist: networkx>=3.6.1
Requires-Dist: numpy>=2.4.0
Requires-Dist: protobuf>=6.33.3
Requires-Dist: pydantic>=2.12.5
Requires-Dist: pyvis>=0.3.2
Requires-Dist: sentence-transformers>=2.0.0
Requires-Dist: torch>=2.9.1
Requires-Dist: transformers>=4.57.3
